edxml_bricks/computing/email.py
edxml_bricks/computing/files.py
edxml_bricks/computing/generic.py
edxml_bricks_computing-3.0.0.dist-info/METADATA
edxml_bricks_computing-3.0.0.dist-info/WHEEL
edxml_bricks_computing-3.0.0.dist-info/top_level.txt
edxml_bricks_computing-3.0.0.dist-info/RECORD
